MC1.v
`timescale 1ps/1ps

module MC1(F, A, B, C, D);

    input A,B,C,D;
    output F;
    wire w1,w2,w3,w4, w5, w6, w7;

    or G1(w1, A, B, C, D);
    or G2(w2, A, B, C, !D);
    or G3(w3, A, B, !C, D);
    or G4(w4, !A, B, C, D);
    or G5(w5, !A, B, !C, D);
    or G6(w6, !A, !B, C, D);
    or G7(w7, !A, !B, !C, D);

    and G8(F, w1, w2, w3, w4, w5, w6, w7);
    
endmodule

MC1_tb.v
module MC1_tb();
    wire t_F;
    reg [3:0] t_input;
    integer i;

    MC1 dut(t_f,t_input[3], t_input[2], t_input[1], t_input[0]);

    initial 
        begin
            t_input = 4'b0000;
            for (i = 1; i <= 15; i++)
                #10 t_input  = i;
        end

    initial
        begin
            $display("Program by JKJulian using Gate-level modelling");
            $monitor("time = %03d ABDCD=%b F=%b", $time, t_input, t_f);
            $dumpfile("MC1.vcd");
            $dumpvars();
        end
endmodule

MC1.vcd
$date
	Sun Feb 16 20:55:11 2025
$end
$version
	Icarus Verilog
$end
$timescale
	1ps
$end
$scope module MC1_tb $end
$var wire 1 ! t_f $end
$var reg 4 " t_input [3:0] $end
$var integer 32 # i [31:0] $end
$scope module dut $end
$var wire 1 $ A $end
$var wire 1 % B $end
$var wire 1 & C $end
$var wire 1 ' D $end
$var wire 1 ! F $end
$var wire 1 ( w1 $end
$var wire 1 ) w2 $end
$var wire 1 * w3 $end
$var wire 1 + w4 $end
$var wire 1 , w5 $end
$var wire 1 - w6 $end
$var wire 1 . w7 $end
$upscope $end
$upscope $end
$enddefinitions $end
$comment Show the parameter values. $end
$dumpall
$end
#0
$dumpvars
1.
1-
1,
1+
1*
1)
0(
0'
0&
0%
0$
b1 #
b0 "
0!
$end
#10
1(
0)
1'
b10 #
b1 "
#20
0*
1)
1&
0'
b11 #
b10 "
#30
1!
1*
1'
b100 #
b11 "
#40
1%
0&
0'
b101 #
b100 "
#50
1'
b110 #
b101 "
#60
1&
0'
b111 #
b110 "
#70
1'
b1000 #
b111 "
#80
0!
0+
1$
0%
0&
0'
b1001 #
b1000 "
#90
1!
1+
1'
b1010 #
b1001 "
#100
0!
0,
1&
0'
b1011 #
b1010 "
#110
1!
1,
1'
b1100 #
b1011 "
#120
0!
0-
1%
0&
0'
b1101 #
b1100 "
#130
1!
1-
1'
b1110 #
b1101 "
#140
0!
0.
1&
0'
b1111 #
b1110 "
#150
1!
1.
1'
b10000 #
b1111 "
